dectrig/__init__.py
dectrig/fast_core.py
dectrig/spline_core.py
dectrig-0.2.0.dist-info/licenses/LICENSE.txt
dectrig-0.2.0.dist-info/METADATA
dectrig-0.2.0.dist-info/WHEEL
dectrig-0.2.0.dist-info/top_level.txt
dectrig-0.2.0.dist-info/RECORD
