Metadata-Version: 2.4
Name: dectrig
Version: 0.2.0
Summary: DecTrig: a decimal-based trigonometric framework using spline interpolations
Home-page: https://github.com/Feynmantle/DecTrig
Author: Chris Holoman
Author-email: Chris Holoman <your-email@example.com>
License: MIT
Project-URL: Homepage, https://github.com/Feynmantle/DecTrig
Requires-Python: >=3.9
License-File: LICENSE.txt
Requires-Dist: numpy
Requires-Dist: scipy
Dynamic: license-file
